sync_fifo.v
module sync_fifo#(parameter DATA_WIDTH=8, parameter DEPTH=8,parameter ADDR_WIDTH=$clog2(DEPTH))(input clk,input rst, input wr_en, input rd_en, input [DATA_WIDTH-1:0]din, output reg [DATA_WIDTH-1:0]dout,output full, output empty);
reg[DATA_WIDTH-1:0] mem[0:DEPTH-1];
reg [ADDR_WIDTH-1:0]wr_ptr;
reg [ADDR_WIDTH-1:0]rd_ptr;
reg [ADDR_WIDTH:0]count;
assign full=(count==DEPTH);
assign empty=(count==0);
always @(posedge clk)
begin
if(rst)
begin
count<=0;
wr_ptr<=0;
rd_ptr<=0;
dout<=0;
end
else
begin
case({wr_en,rd_en})
2'b10:begin
if(!full)
begin
mem[wr_ptr]<=din;
wr_ptr<=wr_ptr+1;
count<=count+1;
end
end
2'b01:begin
if(!empty)
begin
dout<=mem[rd_ptr];
rd_ptr<=rd_ptr+1;
count<=count-1;
end
end
2'b11:begin
if(!full && !empty)
begin
mem[wr_ptr]<=din;
dout<=mem[rd_ptr];
rd_ptr<=rd_ptr+1;
wr_ptr<=wr_ptr+1;
end
else if(empty)
begin
mem[wr_ptr]<=din;
count<=count+1;
wr_ptr<=wr_ptr+1;
end
else if(full)
begin
rd_ptr<=rd_ptr+1;
dout<=mem[rd_ptr];
count<=count-1;
end
end
default:begin
end
endcase
end
end
endmodule

sync_fifo_tb.v
`timescale 1ns/1ps

module sync_fifo_tb;

parameter DATA_WIDTH = 8;
parameter DEPTH = 8;
parameter ADDR_WIDTH = 3;

reg clk;
reg rst;
reg wr_en;
reg rd_en;
reg [DATA_WIDTH-1:0] din;

wire [DATA_WIDTH-1:0] dout;
wire full;
wire empty;

sync_fifo #(
    .DATA_WIDTH(DATA_WIDTH),
    .DEPTH(DEPTH),
    .ADDR_WIDTH(ADDR_WIDTH)
) uut (
    .clk(clk),
    .rst(rst),
    .wr_en(wr_en),
    .rd_en(rd_en),
    .din(din),
    .dout(dout),
    .full(full),
    .empty(empty)
);

always #5 clk = ~clk;
initial begin
    clk = 0;
    rst = 1;
    wr_en = 0;
    rd_en = 0;
    din = 0;
    #10;
    rst = 0;
    @(posedge clk);
    wr_en = 1;
    din = 8'd10;

    @(posedge clk);
    din = 8'd20;

    @(posedge clk);
    din = 8'd30;

    @(posedge clk);
    wr_en = 0;

    rd_en = 1;
    @(posedge clk);

    @(posedge clk);

    rd_en = 0;

    wr_en = 1;
    rd_en = 1;
    din = 8'd40;
    @(posedge clk);

    wr_en = 0;
    rd_en = 0;

    repeat(8)
    begin
        @(posedge clk);
        wr_en = 1;
        din = din + 8'd10;
    end

    @(posedge clk);
    wr_en = 0;

    repeat(8)
    begin
        @(posedge clk);
        rd_en = 1;
    end

    @(posedge clk);
    rd_en = 0;

    #20;
    $finish;
end

initial begin
    $monitor("Time=%0t rst=%b wr=%b rd=%b din=%d dout=%d count? full=%b empty=%b",
             $time, rst, wr_en, rd_en, din, dout, full, empty);
end
initial begin
$dumpfile("sync_fifo_tb.vcd");
$dumpvars(0,sync_fifo_tb);
end
endmodule

sync_fifo_tb.vcd
$date
	Sun Jul 12 14:11:45 2026
$end
$version
	Icarus Verilog
$end
$timescale
	1ps
$end
$scope module sync_fifo_tb $end
$var wire 1 ! full $end
$var wire 1 " empty $end
$var wire 8 # dout [7:0] $end
$var reg 1 $ clk $end
$var reg 8 % din [7:0] $end
$var reg 1 & rd_en $end
$var reg 1 ' rst $end
$var reg 1 ( wr_en $end
$scope module uut $end
$var wire 1 $ clk $end
$var wire 8 ) din [7:0] $end
$var wire 1 & rd_en $end
$var wire 1 ' rst $end
$var wire 1 ( wr_en $end
$var wire 1 ! full $end
$var wire 1 " empty $end
$var reg 4 * count [3:0] $end
$var reg 8 + dout [7:0] $end
$var reg 3 , rd_ptr [2:0] $end
$var reg 3 - wr_ptr [2:0] $end
$upscope $end
$upscope $end
$enddefinitions $end
#0
$dumpvars
bx -
bx ,
bx +
bx *
b0 )
0(
1'
0&
b0 %
0$
bx #
x"
x!
$end
#5000
b0 #
b0 +
b0 ,
b0 -
0!
1"
b0 *
1$
#10000
0$
0'
#15000
0"
b1 *
b1 -
b1010 %
b1010 )
1(
1$
#20000
0$
#25000
b10 *
b10 -
b10100 %
b10100 )
1$
#30000
0$
#35000
b11 *
b11 -
b11110 %
b11110 )
1$
#40000
0$
#45000
b100 *
b100 -
1&
0(
1$
#50000
0$
#55000
b11 *
b1 ,
b1010 #
b1010 +
1$
#60000
0$
#65000
b10 *
b10 ,
b101000 %
b101000 )
1(
1&
1$
#70000
0$
#75000
0&
0(
1$
#80000
0$
#85000
b110010 %
b110010 )
1(
1$
#90000
0$
#95000
b11 *
b101 -
b111100 %
b111100 )
1$
#100000
0$
#105000
b100 *
b110 -
b1000110 %
b1000110 )
1$
#110000
0$
#115000
b101 *
b111 -
b1010000 %
b1010000 )
1$
#120000
0$
#125000
b110 *
b0 -
b1011010 %
b1011010 )
1$
#130000
0$
#135000
b111 *
b1 -
b1100100 %
b1100100 )
1$
#140000
0$
#145000
1!
b1000 *
b10 -
b1101110 %
b1101110 )
1$
#150000
0$
#155000
b1111000 %
b1111000 )
1$
#160000
0$
#165000
0(
1$
#170000
0$
#175000
0!
b111 *
b11 ,
b11110 #
b11110 +
1&
1$
#180000
0$
#185000
b110 *
b100 ,
1$
#190000
0$
#195000
b101 *
b101 ,
b111100 #
b111100 +
1$
#200000
0$
#205000
b100 *
b110 ,
1$
#210000
0$
#215000
b11 *
b111 ,
b1010000 #
b1010000 +
1$
#220000
0$
#225000
b10 *
b0 ,
1$
#230000
0$
#235000
b1 *
b1 ,
b1100100 #
b1100100 +
1$
#240000
0$
#245000
1"
b0 *
b10 ,
1$
#250000
0$
#255000
0&
1$
